world_machine_experiments/__init__.py
world_machine_experiments/shared/__init__.py
world_machine_experiments/shared/acronyms.py
world_machine_experiments/shared/function_variation.py
world_machine_experiments/shared/load_multiple_metrics.py
world_machine_experiments/shared/metric_plot.py
world_machine_experiments/shared/parameter_variation_plots.py
world_machine_experiments/shared/pipeline.py
world_machine_experiments/shared/random.py
world_machine_experiments/shared/save_metrics.py
world_machine_experiments/shared/save_parameters.py
world_machine_experiments/shared/save_plots.py
world_machine_experiments/shared/split_data.py
world_machine_experiments/shared/statistics.py
world_machine_experiments/shared/train_plots.py
world_machine_experiments/tools/__init__.py
world_machine_experiments/tools/export_zip.py
world_machine_experiments/tools/zenodo_upload.py
world_machine_experiments/toy1d/__init__.py
world_machine_experiments/toy1d/channels.py
world_machine_experiments/toy1d/experiment0_protocol_test.py
world_machine_experiments/toy1d/experiment1_configuration_test.py
world_machine_experiments/toy1d/experiment2_best_long.py
world_machine_experiments/toy1d/export_dataset.py
world_machine_experiments/toy1d/base/__init__.py
world_machine_experiments/toy1d/base/autoregressive.py
world_machine_experiments/toy1d/base/data.py
world_machine_experiments/toy1d/base/dataloader.py
world_machine_experiments/toy1d/base/dataset.py
world_machine_experiments/toy1d/base/mask_sensory.py
world_machine_experiments/toy1d/base/metrics.py
world_machine_experiments/toy1d/base/model.py
world_machine_experiments/toy1d/base/plot.py
world_machine_experiments/toy1d/base/simple_shift_loss.py
world_machine_experiments/toy1d/base/train.py
world_machine_experiments/toy1d/multiple/__init__.py
world_machine_experiments/toy1d/multiple/multiple_runs.py
world_machine_experiments/toy1d/parameter_variation/__init__.py
world_machine_experiments/toy1d/parameter_variation/parameter_variation.py
world_machine_experiments-0.2.dist-info/licenses/LICENSE
world_machine_experiments-0.2.dist-info/METADATA
world_machine_experiments-0.2.dist-info/WHEEL
world_machine_experiments-0.2.dist-info/top_level.txt
world_machine_experiments-0.2.dist-info/RECORD
