Metadata-Version: 2.4
Name: world_machine_experiments
Version: 0.2
Summary: Experiments of the World Machine project, that investigates the concept and creation of computational world models
Author-email: Elton Cardoso do Nascimento <e233840@dac.unicamp.br>
Project-URL: Homepage, https://h-iaac.github.io/WorldMachine/
Project-URL: Bug Tracker, https://github.com/EltonCN/WorldMachine/issues
Classifier: Programming Language :: Python :: 3
Classifier: Operating System :: OS Independent
Classifier: Topic :: Scientific/Engineering
Classifier: Topic :: Scientific/Engineering :: Artificial Intelligence
Classifier: Intended Audience :: Science/Research
Requires-Python: >=3.10
License-File: LICENSE
Requires-Dist: torch
Requires-Dist: tensordict
Requires-Dist: numpy
Requires-Dist: docstring_parser
Requires-Dist: sf-hamilton
Requires-Dist: scipy
Requires-Dist: pysdtw
Requires-Dist: seaborn
Requires-Dist: networkx[default]
Requires-Dist: pydot
Requires-Dist: graphviz
Requires-Dist: zenodo_client
Dynamic: license-file
